MANIFEST.in
README
setup.py
timetra/__init__.py
timetra.diary.egg-info/PKG-INFO
timetra.diary.egg-info/SOURCES.txt
timetra.diary.egg-info/dependency_links.txt
timetra.diary.egg-info/entry_points.txt
timetra.diary.egg-info/not-zip-safe
timetra.diary.egg-info/requires.txt
timetra.diary.egg-info/top_level.txt
timetra/diary/__init__.py
timetra/diary/app.py
timetra/diary/caching.py
timetra/diary/cli_old.py
timetra/diary/diary.py
timetra/diary/formatdelta.py
timetra/diary/models.py
timetra/diary/notification.py
timetra/diary/storage.py
timetra/diary/term.py
timetra/diary/timer.py
timetra/diary/utils.py
timetra/diary/curses/__init__.py
timetra/diary/curses/widgets.py
timetra/diary/reporting/__init__.py
timetra/diary/reporting/drift.py
timetra/diary/reporting/methodology.py
timetra/diary/reporting/prediction.py