Metadata-Version: 1.1
Name: timetra.diary
Version: 0.1.0
Summary: Diary with CLI + YAML
Home-page: https://github.com/neithere/timetra.diary
Author: Andrey Mikhaylenko
Author-email: neithere@gmail.com
License: GNU Lesser General Public License (LGPL), Version 3
Download-URL: https://github.com/neithere/timetra.diary/archive/master.zip
Keywords: cli command line time tracking timer diary
Platform: UNKNOWN
Classifier: Development Status :: 3 - Alpha
Classifier: Environment :: Console
Classifier: Intended Audience :: Developers
Classifier: Intended Audience :: End Users/Desktop
Classifier: License :: OSI Approved :: GNU Library or Lesser General Public License (LGPL)
Classifier: Programming Language :: Python
Classifier: Topic :: Utilities
Classifier: Topic :: Software Development :: Libraries :: Python Modules
